kjutils/PriceStock.py
kjutils/__init__.py
kjutils/kjutils.py
kjutils-1.7.dist-info/METADATA
kjutils-1.7.dist-info/WHEEL
kjutils-1.7.dist-info/top_level.txt
kjutils-1.7.dist-info/RECORD
